Workbook

Sheet Dashboard
A1: BOND BUY / SELL DASHBOARD
A3: Συμπέρασμα με βάση Intrinsic Value, YTM, RCY, Duration και Risk Score. Δεν αποτελεί επενδυτική συμβουλή.
A5: Τελική ένδειξη | B5: =Analysis!$B$26 -> ΜΗ ΑΓΟΡΑ / ΠΕΡΙΜΕΝΕ | D5: Επίπεδο κινδύνου | E5: =Risk!$B$15 -> Μέσος
A7: Δείκτης | B7: Τιμή | C7: Ερμηνεία | E7: Δείκτης | F7: Τιμή | G7: Ερμηνεία
A8: Intrinsic Value (IV) | B8: =Analysis!$B$14 -> 987.01315 | C8: Αν IV > MP, το ομόλογο φαίνεται υποτιμημένο. | E8: Macaulay Duration | F8: =Analysis!$B$21 -> 8.1912191 | G8: Σταθμισμένος χρόνος είσπραξης cash flows.
A9: IV / Κόστος | B9: =Analysis!$B$15 -> 0.99998292 | C9: Πάνω από 1 σημαίνει ότι η θεωρητική αξία ξεπερνά το κόστος. | E9: Modified Duration | F9: =Analysis!$B$22 -> 8.0094923 | G9: Ευαισθησία τιμής σε μεταβολή απόδοσης.
A10: MP-FV | B10: =Analysis!$B$25 -> Discount / κάτω από την ονομαστική αξία | C10: Discount / Premium / Par. | E10: Price impact για Δy | F10: =Analysis!$B$23 -> -0.080094923 | G10: Προσέγγιση % μεταβολής τιμής.
A11: Current Yield | B11: =Analysis!$B$16 -> 0.044324894 | C11: Ετήσιο κουπόνι προς τρέχουσα τιμή. | E11: Estimated Price | F11: =Analysis!$B$24 -> 907.97391 | G11: Τιμή μετά το σενάριο Δy.
A12: YTM καθαρό | B12: =Analysis!$B$18 -> 0.045377868 | C12: Απόδοση έως λήξη μετά προμήθειες/φόρους. | E12: Risk Score | F12: =Risk!$B$14 -> 2.57 | G12: Συνδυαστικός δείκτης κινδύνου.
A13: AYTM approx | B13: =Analysis!$B$19 -> 0.045341037 | C13: Προσεγγιστικός τύπος από σημειώσεις. | E13: Συνολική αξία θέσης | F13: =Analysis!$B$29 -> 987.03 | G13: Κόστος για το πλήθος ομολόγων.
A14: RCY | B14: =Analysis!$B$20 -> 0.038311705 | C14: Απόδοση με επανεπένδυση κουπονιών. | E14: Αιτιολόγηση | F14: =Analysis!$B$27 -> Βάση=Αγορά. IV/Κόστος=001x, YTM καθαρό=005%, r=005%, κίνδυνος=Μέσος. | G14: Σύντομη λογική συμπεράσματος.
A16: Πρακτικός κανόνας αγοράς/πώλησης
A17: Αγορά | B17: όταν IV > MP με περιθώριο και YTM ≥ απαιτούμενη απόδοση και ο κίνδυνος δεν είναι υψηλός.
A18: Πώληση / μη αγορά | B18: όταν IV < MP με περιθώριο ή YTM < απαιτούμενη απόδοση ή ο κίνδυνος βγαίνει υψηλός.
A19: Διακράτηση | B19: όταν το ομόλογο είναι περίπου δίκαια τιμολογημένο ή τα σήματα είναι μικτά.
A20: Μalkiel | B20: Απόδοση/επιτόκιο αγοράς ↑ ⇒ τιμή ↓. Απόδοση/επιτόκιο αγοράς ↓ ⇒ τιμή ↑.
A21: Προσοχή | B21: Το αρχείο είναι εργαλείο εκπαίδευσης/ανάλυσης και όχι εξατομικευμένη επενδυτική σύσταση.

Sheet Inputs
A1: ΕΙΣΟΔΟΙ ΓΙΑ ΑΝΑΛΥΣΗ ΟΜΟΛΟΓΟΥ
A3: Συμπλήρωσε τα κίτρινα κελιά. Τα αποτελέσματα βγαίνουν αυτόματα στο Dashboard.
A4: Ονομασία / ISIN | B4: U.S. Treasury Note 4,375% 15/05/2036 — US91282CQQ77 | C4: Κείμενο αναγνώρισης ομολόγου.
A5: Εκδότης | B5: United States Treasury / U.S. Government | C5: Ποιος είναι ο εκδότης.
A6: Τύπος ομολόγου | B6: Treasury/Government | C6: Corporate / Treasury-Government / Municipal-Local Authority.
A7: Νόμισμα αγοράς/πώλησης | B7: USD | C7: Νόμισμα διαπραγμάτευσης.
A8: Σειρά προτεραιότητας | B8: Senior | C8: Senior ή Subordinated.
A9: Callable; | B9: Όχι | C9: Αν ο εκδότης μπορεί να το ανακαλέσει πριν τη λήξη.
A10: Ρευστότητα αγοράς | B10: Υψηλή | C10: Πόσο εύκολα μπορεί να αγοραστεί/πωληθεί.
A11: Πιστοληπτική διαβάθμιση | B11: AAA | C11: Rating. Αν δεν υπάρχει, βάλε Not rated.
A12: Ονομαστική αξία FV ανά ομόλογο | B12: 1000 | C12: Face value / ποσό αποπληρωμής στη λήξη.
A13: Αγοραία τιμή MP ανά ομόλογο | B13: 987.03 | C13: Market price / καθαρή τιμή αγοράς πριν προμήθειες.
A14: Κουπόνι ετήσιο % k | B14: 0.04375 | C14: Ετήσιο κουπόνι ως ποσοστό της ονομαστικής αξίας.
A15: Συχνότητα κουπονιού ανά έτος | B15: 2 | C15: 1=ετήσιο, 2=εξαμηνιαίο, 4=τριμηνιαίο, 12=μηνιαίο.
A16: Χρόνια έως τη λήξη n | B16: 10 | C16: Χρόνια μέχρι αποπληρωμή FV.
A17: Απαιτούμενη απόδοση r / επιτόκιο αγοράς | B17: 0.04538 | C17: Η απόδοση που ζητάς/συγκριτική απόδοση αγοράς.
A18: Επανεπένδυση κουπονιών για RCY | B18: 0 | C18: Ετήσιος ρυθμός επανεπένδυσης κουπονιών.
A19: Προμήθειες αγοράς/πώλησης % | B19: 0 | C19: Ποσοστό κόστους συναλλαγής.
A20: Φορολογία κουπονιών % | B20: 0 | C20: Φόρος πάνω στα κουπόνια, αν εφαρμόζεται.
A21: Πλήθος ομολόγων | B21: 1 | C21: Πόσα ομόλογα θα αγοράσεις/πουλήσεις.
A22: Νόμισμα βάσης επενδυτή | B22: EUR | C22: Για ένδειξη συναλλαγματικού κινδύνου.
A23: Αναμενόμενη μεταβολή απόδοσης Δy | B23: 0.01 | C23: Π.χ. +1% = 0,01. Χρησιμοποιείται για price impact.
A24: Όριο υποτίμησης/υπερτίμησης IV vs MP | B24: 0.02 | C24: Π.χ. 2% περιθώριο για BUY/SELL/HOLD.
A25: Βάση αξιολόγησης | B25: Αγορά | C25: Αγορά / Πώληση / Διακράτηση.

Sheet Analysis
A1: ΥΠΟΛΟΓΙΣΜΟΙ ΔΕΙΚΤΩΝ ΟΜΟΛΟΓΟΥ
A3: Οι τύποι βασίζονται στις σημειώσεις: FV, MP, IV, YTM, AYTM, RCY, Current Yield, Duration.
A4: FV ανά ομόλογο | B4: =Inputs!$B$12 -> 1000 | C4: €
A5: MP ανά ομόλογο | B5: =Inputs!$B$13 -> 987.03 | C5: €
A6: Προμήθεια ανά ομόλογο | B6: =B5*Inputs!$B$19 -> 0 | C6: €
A7: Καθαρό κόστος αγοράς | B7: =B5+B6 -> 987.03 | C7: €
A8: Καθαρό προϊόν πώλησης | B8: =B5-B6 -> 987.03 | C8: €
A9: Ετήσιο κουπόνι C (μικτό) | B9: =Inputs!$B$14*B4 -> 43.75 | C9: € / έτος
A10: Ετήσιο κουπόνι C (καθαρό) | B10: =B9*(1-Inputs!$B$20) -> 43.75 | C10: € / έτος
A11: Κουπόνι ανά περίοδο | B11: =B10/Inputs!$B$15 -> 21.875 | C11: € / περίοδο
A12: Σύνολο περιόδων έως λήξη | B12: =Inputs!$B$16*Inputs!$B$15 -> 20 | C12: περίοδοι
A13: Περιοδικό required yield | B13: =Inputs!$B$17/Inputs!$B$15 -> 0.02269 | C13: ανά περίοδο
A14: Intrinsic Value (IV) με r | B14: =IF(B13=0,B11*B12+B4,B11*(1-POWER(1+B13,-B12))/B13+B4/POWER(1+B13,B12)) -> 987.01315 | C14: €
A15: IV / Καθαρό κόστος αγοράς | B15: =IFERROR(B14/B7,"") -> 0.99998292 | C15: x
A16: Τρέχουσα απόδοση (Current Yield) | B16: =IFERROR(B9/B5,"") -> 0.044324894 | C16: %
A17: YTM ακριβές (μικτό) | B17: =IFERROR(RATE(B12,B9/Inputs!$B$15,-B5,B4)*Inputs!$B$15,"") -> 0.045377868 | C17: %
A18: YTM καθαρό μετά προμηθειών/φόρων | B18: =IFERROR(RATE(B12,B11,-B7,B4)*Inputs!$B$15,"") -> 0.045377868 | C18: %
A19: AYTM κατά προσέγγιση | B19: =IFERROR((B10+(B4-B7)/Inputs!$B$16)/((B4+B7)/2),"") -> 0.045341037 | C19: %
A20: RCY με επανεπένδυση κουπονιών | B20: =IFERROR(POWER((B4+FV(Inputs!$B$18/Inputs!$B$15,B12,-B11,0,0))/B7,1/Inputs!$B$16)-1,"") -> 0.038311705 | C20: %
A21: Macaulay Duration | B21: =SUM(Cash_Flows!$G$6:$G$605) -> 8.1912191 | C21: χρόνια
A22: Modified Duration | B22: =IFERROR(B21/(1+B18/Inputs!$B$15),"") -> 8.0094923 | C22: χρόνια
A23: Εκτιμώμενη % μεταβολή τιμής για Δy | B23: =IFERROR(-B22*Inputs!$B$23,"") -> -0.080094923 | C23: %
A24: Εκτιμώμενη τιμή μετά Δy | B24: =IFERROR(B5*(1+B23),"") -> 907.97391 | C24: €
A25: Σχέση MP-FV | B25: =IF(ABS(B5-B4)/B4<0.001,"At par / κοντά στην ονομαστική αξία",IF(B5>B4,"Premium / πάνω από την ονομαστική αξία","Discount / κάτω από την ονομαστική αξία")) -> Discount / κάτω από την ονομαστική αξία | C25: κείμενο
A26: Συμπέρασμα | B26: =IF(TRIM(Inputs!$B$25)="Αγορά",IF(B28="Υψηλός","ΜΗ ΑΓΟΡΑ / ΥΨΗΛΟΣ ΚΙΝΔΥΝΟΣ",IF(AND(B15>=1+Inputs!$B$24,B18>=Inputs!$B$17),"ΑΓΟΡΑ",IF(OR(B15>=1,B18>=Inputs!$B$17),"ΕΠΙΛΕΚΤΙΚΗ ΑΓΟΡΑ / ΜΕ ΠΡΟΣΟΧΗ","ΜΗ ΑΓΟΡΑ / ΠΕΡΙΜΕΝΕ"))),IF(TRIM(Inputs!$B$25)="Πώληση",IF(B28="Υψηλός","ΠΩΛΗΣΗ / ΕΛΕΓΧΟΣ ΚΙΝΔΥΝΟΥ",IF(OR(B15<=1-Inputs!$B$24,B18<Inputs!$B$17),"ΠΩΛΗΣΗ","ΜΗ ΠΩΛΗΣΗ / ΔΙΑΚΡΑΤΗΣΗ")),IF(TRIM(Inputs!$B$25)="Διακράτηση",IF(B28="Υψηλός","ΕΠΑΝΕΞΕΤΑΣΗ / ΠΙΘΑΝΗ ΠΩΛΗΣΗ",IF(OR(B15<=1-Inputs!$B$24,B18<Inputs!$B$17),"ΔΙΑΚΡΑΤΗΣΗ ΜΕ ΠΡΟΣΟΧΗ / ΕΠΑΝΕΞΕΤΑΣΗ","ΔΙΑΚΡΑΤΗΣΗ")),"ΕΛΕΓΞΕ ΒΑΣΗ ΑΞΙΟΛΟΓΗΣΗΣ"))) -> ΜΗ ΑΓΟΡΑ / ΠΕΡΙΜΕΝΕ | C26: κείμενο
A27: Αιτιολόγηση | B27: ="Βάση="&Inputs!$B$25&". IV/Κόστος="&TEXT(B15,"0.00x")&", YTM καθαρό="&TEXT(B18,"0.00%")&", r="&TEXT(Inputs!$B$17,"0.00%")&", κίνδυνος="&B28&"." -> Βάση=Αγορά. IV/Κόστος=001x, YTM καθαρό=005%, r=005%, κίνδυνος=Μέσος. | C27: κείμενο
A28: Επίπεδο κινδύνου | B28: =Risk!$B$15 -> Μέσος | C28: κείμενο
A29: Συνολική αξία θέσης | B29: =B7*Inputs!$B$21 -> 987.03 | C29: €

Sheet Cash_Flows
A1: CASH FLOWS ΚΑΙ DURATION
A3: Χρησιμοποιείται για Macaulay Duration και Modified Duration. Υποστηρίζει έως 600 περιόδους.
A5: Περίοδος | B5: Χρόνος (έτη) | C5: Cash Flow | D5: Discount Factor | E5: PV Cash Flow | F5: Βάρος | G5: Weighted Time
A6: 1 | B6: =IF(A6<=Analysis!$B$12,A6/Inputs!$B$15,0) -> 0.5 | C6: =IF(A6<=Analysis!$B$12,Analysis!$B$11+IF(A6=Analysis!$B$12,Analysis!$B$4,0),0) -> 21.875 | D6: =IFERROR(IF(A6<=Analysis!$B$12,1/POWER(1+Analysis!$B$18/Inputs!$B$15,A6),0),0) -> 0.97781443 | E6: =C6*D6 -> 21.389691 | F6: =IFERROR(E6/SUM($E$6:$E$605),0) -> 0.02167076 | G6: =B6*F6 -> 0.01083538
A7: 2 | B7: =IF(A7<=Analysis!$B$12,A7/Inputs!$B$15,0) -> 1 | C7: =IF(A7<=Analysis!$B$12,Analysis!$B$11+IF(A7=Analysis!$B$12,Analysis!$B$4,0),0) -> 21.875 | D7: =IFERROR(IF(A7<=Analysis!$B$12,1/POWER(1+Analysis!$B$18/Inputs!$B$15,A7),0),0) -> 0.95612107 | E7: =C7*D7 -> 20.915148 | F7: =IFERROR(E7/SUM($E$6:$E$605),0) -> 0.021189982 | G7: =B7*F7 -> 0.021189982
A8: 3 | B8: =IF(A8<=Analysis!$B$12,A8/Inputs!$B$15,0) -> 1.5 | C8: =IF(A8<=Analysis!$B$12,Analysis!$B$11+IF(A8=Analysis!$B$12,Analysis!$B$4,0),0) -> 21.875 | D8: =IFERROR(IF(A8<=Analysis!$B$12,1/POWER(1+Analysis!$B$18/Inputs!$B$15,A8),0),0) -> 0.93490898 | E8: =C8*D8 -> 20.451134 | F8: =IFERROR(E8/SUM($E$6:$E$605),0) -> 0.020719871 | G8: =B8*F8 -> 0.031079806
A9: 4 | B9: =IF(A9<=Analysis!$B$12,A9/Inputs!$B$15,0) -> 2 | C9: =IF(A9<=Analysis!$B$12,Analysis!$B$11+IF(A9=Analysis!$B$12,Analysis!$B$4,0),0) -> 21.875 | D9: =IFERROR(IF(A9<=Analysis!$B$12,1/POWER(1+Analysis!$B$18/Inputs!$B$15,A9),0),0) -> 0.91416749 | E9: =C9*D9 -> 19.997414 | F9: =IFERROR(E9/SUM($E$6:$E$605),0) -> 0.020260189 | G9: =B9*F9 -> 0.040520377
A10: 5 | B10: =IF(A10<=Analysis!$B$12,A10/Inputs!$B$15,0) -> 2.5 | C10: =IF(A10<=Analysis!$B$12,Analysis!$B$11+IF(A10=Analysis!$B$12,Analysis!$B$4,0),0) -> 21.875 | D10: =IFERROR(IF(A10<=Analysis!$B$12,1/POWER(1+Analysis!$B$18/Inputs!$B$15,A10),0),0) -> 0.89388617 | E10: =C10*D10 -> 19.55376 | F10: =IFERROR(E10/SUM($E$6:$E$605),0) -> 0.019810705 | G10: =B10*F10 -> 0.049526762
A11: 6 | B11: =IF(A11<=Analysis!$B$12,A11/Inputs!$B$15,0) -> 3 | C11: =IF(A11<=Analysis!$B$12,Analysis!$B$11+IF(A11=Analysis!$B$12,Analysis!$B$4,0),0) -> 21.875 | D11: =IFERROR(IF(A11<=Analysis!$B$12,1/POWER(1+Analysis!$B$18/Inputs!$B$15,A11),0),0) -> 0.8740548 | E11: =C11*D11 -> 19.119949 | F11: =IFERROR(E11/SUM($E$6:$E$605),0) -> 0.019371193 | G11: =B11*F11 -> 0.058113579
A12: 7 | B12: =IF(A12<=Analysis!$B$12,A12/Inputs!$B$15,0) -> 3.5 | C12: =IF(A12<=Analysis!$B$12,Analysis!$B$11+IF(A12=Analysis!$B$12,Analysis!$B$4,0),0) -> 21.875 | D12: =IFERROR(IF(A12<=Analysis!$B$12,1/POWER(1+Analysis!$B$18/Inputs!$B$15,A12),0),0) -> 0.85466339 | E12: =C12*D12 -> 18.695762 | F12: =IFERROR(E12/SUM($E$6:$E$605),0) -> 0.018941432 | G12: =B12*F12 -> 0.066295012
A13: 8 | B13: =IF(A13<=Analysis!$B$12,A13/Inputs!$B$15,0) -> 4 | C13: =IF(A13<=Analysis!$B$12,Analysis!$B$11+IF(A13=Analysis!$B$12,Analysis!$B$4,0),0) -> 21.875 | D13: =IFERROR(IF(A13<=Analysis!$B$12,1/POWER(1+Analysis!$B$18/Inputs!$B$15,A13),0),0) -> 0.8357022 | E13: =C13*D13 -> 18.280986 | F13: =IFERROR(E13/SUM($E$6:$E$605),0) -> 0.018521206 | G13: =B13*F13 -> 0.074084823
A14: 9 | B14: =IF(A14<=Analysis!$B$12,A14/Inputs!$B$15,0) -> 4.5 | C14: =IF(A14<=Analysis!$B$12,Analysis!$B$11+IF(A14=Analysis!$B$12,Analysis!$B$4,0),0) -> 21.875 | D14: =IFERROR(IF(A14<=Analysis!$B$12,1/POWER(1+Analysis!$B$18/Inputs!$B$15,A14),0),0) -> 0.81716167 | E14: =C14*D14 -> 17.875412 | F14: =IFERROR(E14/SUM($E$6:$E$605),0) -> 0.018110302 | G14: =B14*F14 -> 0.08149636
A15: 10 | B15: =IF(A15<=Analysis!$B$12,A15/Inputs!$B$15,0) -> 5 | C15: =IF(A15<=Analysis!$B$12,Analysis!$B$11+IF(A15=Analysis!$B$12,Analysis!$B$4,0),0) -> 21.875 | D15: =IFERROR(IF(A15<=Analysis!$B$12,1/POWER(1+Analysis!$B$18/Inputs!$B$15,A15),0),0) -> 0.79903248 | E15: =C15*D15 -> 17.478835 | F15: =IFERROR(E15/SUM($E$6:$E$605),0) -> 0.017708515 | G15: =B15*F15 -> 0.088542575
A16: 11 | B16: =IF(A16<=Analysis!$B$12,A16/Inputs!$B$15,0) -> 5.5 | C16: =IF(A16<=Analysis!$B$12,Analysis!$B$11+IF(A16=Analysis!$B$12,Analysis!$B$4,0),0) -> 21.875 | D16: =IFERROR(IF(A16<=Analysis!$B$12,1/POWER(1+Analysis!$B$18/Inputs!$B$15,A16),0),0) -> 0.78130549 | E16: =C16*D16 -> 17.091058 | F16: =IFERROR(E16/SUM($E$6:$E$605),0) -> 0.017315641 | G16: =B16*F16 -> 0.095236028
A17: 12 | B17: =IF(A17<=Analysis!$B$12,A17/Inputs!$B$15,0) -> 6 | C17: =IF(A17<=Analysis!$B$12,Analysis!$B$11+IF(A17=Analysis!$B$12,Analysis!$B$4,0),0) -> 21.875 | D17: =IFERROR(IF(A17<=Analysis!$B$12,1/POWER(1+Analysis!$B$18/Inputs!$B$15,A17),0),0) -> 0.76397179 | E17: =C17*D17 -> 16.711883 | F17: =IFERROR(E17/SUM($E$6:$E$605),0) -> 0.016931484 | G17: =B17*F17 -> 0.1015889
... A605: 600 | B605: =IF(A605<=Analysis!$B$12,A605/Inputs!$B$15,0) -> 0 | C605: =IF(A605<=Analysis!$B$12,Analysis!$B$11+IF(A605=Analysis!$B$12,Analysis!$B$4,0),0) -> 0 | D605: =IFERROR(IF(A605<=Analysis!$B$12,1/POWER(1+Analysis!$B$18/Inputs!$B$15,A605),0),0) -> 0 | E605: =C605*D605 -> 0 | F605: =IFERROR(E605/SUM($E$6:$E$605),0) -> 0 | G605: =B605*F605 -> 0

Sheet Risk
A1: ΑΝΑΛΥΣΗ ΚΙΝΔΥΝΟΥ
A3: Risk score: πιστωτικός, επιτοκιακός, ρευστότητας, συναλλαγματικός, προτεραιότητας, callable.
A5: Παράγοντας | B5: Input/Δείκτης | C5: Score | D5: Βάρος | E5: Weighted Score | F5: Ερμηνεία
A6: Πιστωτικός κίνδυνος / Rating | B6: =Inputs!$B$11 -> AAA | C6: =IFERROR(VLOOKUP(Inputs!$B$11,Lists!$O$2:$P$11,2,FALSE),7) -> 1 | D6: 0.35 | E6: =C6*D6 -> 0.35 | F6: Χαμηλότερο score σημαίνει ισχυρότερη διαβάθμιση.
A7: Τύπος ομολόγου | B7: =Inputs!$B$6 -> Treasury/Government | C7: =IFERROR(VLOOKUP(Inputs!$B$6,Lists!$AA$2:$AB$4,2,FALSE),4) -> 1 | D7: 0.1 | E7: =C7*D7 -> 0.1 | F7: Κρατικά συνήθως χαμηλότερος κίνδυνος, εταιρικά υψηλότερος.
A8: Επιτοκιακός κίνδυνος / Duration | B8: =Analysis!$B$22 -> 8.0094923 | C8: =IF(B8<3,1,IF(B8<=6,3,6)) -> 6 | D8: 0.25 | E8: =C8*D8 -> 1.5 | F8: Μεγαλύτερο duration σημαίνει μεγαλύτερη ευαισθησία τιμής.
A9: Ρευστότητα | B9: =Inputs!$B$10 -> Υψηλή | C9: =IFERROR(VLOOKUP(Inputs!$B$10,Lists!$R$2:$S$4,2,FALSE),3) -> 1 | D9: 0.1 | E9: =C9*D9 -> 0.1 | F9: Χαμηλή ρευστότητα δυσκολεύει πώληση/αγορά στην επιθυμητή τιμή.
A10: Συναλλαγματικός κίνδυνος | B10: =IF(Inputs!$B$7=Inputs!$B$22,"Ίδιο νόμισμα","Διαφορετικό νόμισμα") -> Διαφορετικό νόμισμα | C10: =IF(Inputs!$B$7=Inputs!$B$22,1,5) -> 5 | D10: 0.08 | E10: =C10*D10 -> 0.4 | F10: Αν νόμισμα ομολόγου ≠ νόμισμα βάσης, υπάρχει FX κίνδυνος.
A11: Σειρά προτεραιότητας | B11: =Inputs!$B$8 -> Senior | C11: =IFERROR(VLOOKUP(Inputs!$B$8,Lists!$U$2:$V$3,2,FALSE),3) -> 1 | D11: 0.07 | E11: =C11*D11 -> 0.07 | F11: Subordinated πληρώνεται μετά τα senior σε περίπτωση προβλήματος.
A12: Callable | B12: =Inputs!$B$9 -> Όχι | C12: =IFERROR(VLOOKUP(Inputs!$B$9,Lists!$X$2:$Y$3,2,FALSE),2) -> 1 | D12: 0.05 | E12: =C12*D12 -> 0.05 | F12: Callable σημαίνει ότι ο εκδότης μπορεί να ανακαλέσει το ομόλογο.
A14: Συνολικό Risk Score | B14: =SUM(E6:E12) -> 2.57
A15: Επίπεδο κινδύνου | B15: =IF(B14<=2.5,"Χαμηλός",IF(B14<=4.5,"Μέσος","Υψηλός")) -> Μέσος
A16: Σύντομη ερμηνεία | B16: ="Risk Score="&TEXT(B14,"0.00")&" άρα κίνδυνος: "&B15&". Έλεγξε κυρίως rating, duration και ρευστότητα." -> Risk Score=003 άρα κίνδυνος: Μέσος. Έλεγξε κυρίως rating, duration και ρευστότητα.

Sheet Sensitivity
A1: ΕΥΑΙΣΘΗΣΙΑ ΤΙΜΗΣ ΣΕ ΜΕΤΑΒΟΛΗ ΑΠΟΔΟΣΗΣ
A3: Με βάση τον κανόνα Duration: %ΔP ≈ -Modified Duration × Δy. Περιλαμβάνεται και exact reprice.
A5: Δy | B5: Duration approx %ΔP | C5: Duration approx Price | D5: Exact Reprice | E5: Διαφορά Exact-Approx
A6: -0.02 | B6: =-Analysis!$B$22*A6 -> 0.16018985 | C6: =Analysis!$B$5*(1+B6) -> 1145.1422 | D6: =IFERROR(IF((Analysis!$B$18+A6)/Inputs!$B$15=0,Analysis!$B$11*Analysis!$B$12+Analysis!$B$4,Analysis!$B$11*(1-POWER(1+(Analysis!$B$18+A6)/Inputs!$B$15,-Analysis!$B$12))/((Analysis!$B$18+A6)/Inputs!$B$15)+Analysis!$B$4/POWER(1+(Analysis!$B$18+A6)/Inputs!$B$15,Analysis!$B$12)),"") -> 1161.3646 | E6: =D6-C6 -> 16.222392
A7: -0.01 | B7: =-Analysis!$B$22*A7 -> 0.080094923 | C7: =Analysis!$B$5*(1+B7) -> 1066.0861 | D7: =IFERROR(IF((Analysis!$B$18+A7)/Inputs!$B$15=0,Analysis!$B$11*Analysis!$B$12+Analysis!$B$4,Analysis!$B$11*(1-POWER(1+(Analysis!$B$18+A7)/Inputs!$B$15,-Analysis!$B$12))/((Analysis!$B$18+A7)/Inputs!$B$15)+Analysis!$B$4/POWER(1+(Analysis!$B$18+A7)/Inputs!$B$15,Analysis!$B$12)),"") -> 1069.9996 | E7: =D7-C7 -> 3.9135136
A8: 0 | B8: =-Analysis!$B$22*A8 -> 0 | C8: =Analysis!$B$5*(1+B8) -> 987.03 | D8: =IFERROR(IF((Analysis!$B$18+A8)/Inputs!$B$15=0,Analysis!$B$11*Analysis!$B$12+Analysis!$B$4,Analysis!$B$11*(1-POWER(1+(Analysis!$B$18+A8)/Inputs!$B$15,-Analysis!$B$12))/((Analysis!$B$18+A8)/Inputs!$B$15)+Analysis!$B$4/POWER(1+(Analysis!$B$18+A8)/Inputs!$B$15,Analysis!$B$12)),"") -> 987.03 | E8: =D8-C8 -> -2.4670044e-11
A9: 0.01 | B9: =-Analysis!$B$22*A9 -> -0.080094923 | C9: =Analysis!$B$5*(1+B9) -> 907.97391 | D9: =IFERROR(IF((Analysis!$B$18+A9)/Inputs!$B$15=0,Analysis!$B$11*Analysis!$B$12+Analysis!$B$4,Analysis!$B$11*(1-POWER(1+(Analysis!$B$18+A9)/Inputs!$B$15,-Analysis!$B$12))/((Analysis!$B$18+A9)/Inputs!$B$15)+Analysis!$B$4/POWER(1+(Analysis!$B$18+A9)/Inputs!$B$15,Analysis!$B$12)),"") -> 911.62587 | E9: =D9-C9 -> 3.6519658
A10: 0.02 | B10: =-Analysis!$B$22*A10 -> -0.16018985 | C10: =Analysis!$B$5*(1+B10) -> 828.91782 | D10: =IFERROR(IF((Analysis!$B$18+A10)/Inputs!$B$15=0,Analysis!$B$11*Analysis!$B$12+Analysis!$B$4,Analysis!$B$11*(1-POWER(1+(Analysis!$B$18+A10)/Inputs!$B$15,-Analysis!$B$12))/((Analysis!$B$18+A10)/Inputs!$B$15)+Analysis!$B$4/POWER(1+(Analysis!$B$18+A10)/Inputs!$B$15,Analysis!$B$12)),"") -> 843.04383 | E10: =D10-C10 -> 14.126011
A12: Σημείωση | B12: Όσο αυξάνεται η απόδοση/επιτόκιο αγοράς, η τιμή του ομολόγου συνήθως μειώνεται. Όσο μειώνεται η απόδοση, η τιμή αυξάνεται.

Sheet Portfolio
A1: ΧΑΡΤΟΦΥΛΑΚΙΟ ΟΜΟΛΟΓΩΝ ΚΑΙ PORTFOLIO DURATION
A3: Προαιρετικά: βάλε πολλά ομόλογα για να δεις συνολικό duration χαρτοφυλακίου.
A5: Ομόλογο | B5: Αξία Θέσης | C5: Βάρος | D5: Modified Duration | E5: Risk Score | F5: Risk Level | G5: Weighted Duration | H5: Weighted Risk
A6: =Inputs!$B$4 -> U.S. Treasury Note 4,375% 15/05/2036 — US91282CQQ77 | B6: =Analysis!$B$29 -> 987.03 | C6: =IFERROR(B6/SUM($B$6:$B$20),0) -> 0.328039 | D6: =Analysis!$B$22 -> 8.0094923 | E6: =Risk!$B$14 -> 2.57 | F6: =Risk!$B$15 -> Μέσος | G6: =C6*D6 -> 2.6274259 | H6: =C6*E6 -> 0.84306024
A7: GGB 3,875% 15/06/2028 — GR0114033583 | B7: 1024.4 | C7: =IFERROR(B7/SUM($B$6:$B$20),0) -> 0.34045891 | D7: 1.9132539 | E7: 1.9 | F7: Χαμηλός | G7: =C7*D7 -> 0.65138435 | H7: =C7*E7 -> 0.64687193
A8: U.S. Treasury Note 4,125% 31/05/2031 — US91282CQU89 | B8: 997.45 | C8: =IFERROR(B8/SUM($B$6:$B$20),0) -> 0.33150209 | D8: 4.4747327 | E8: 1.82 | F8: Χαμηλός | G8: =C8*D8 -> 1.4833832 | H8: =C8*E8 -> 0.6033338
C9: =IFERROR(B9/SUM($B$6:$B$20),0) -> 0 | G9: =C9*D9 -> 0 | H9: =C9*E9 -> 0
C10: =IFERROR(B10/SUM($B$6:$B$20),0) -> 0 | G10: =C10*D10 -> 0 | H10: =C10*E10 -> 0
C11: =IFERROR(B11/SUM($B$6:$B$20),0) -> 0 | G11: =C11*D11 -> 0 | H11: =C11*E11 -> 0
C12: =IFERROR(B12/SUM($B$6:$B$20),0) -> 0 | G12: =C12*D12 -> 0 | H12: =C12*E12 -> 0
C13: =IFERROR(B13/SUM($B$6:$B$20),0) -> 0 | G13: =C13*D13 -> 0 | H13: =C13*E13 -> 0
C14: =IFERROR(B14/SUM($B$6:$B$20),0) -> 0 | G14: =C14*D14 -> 0 | H14: =C14*E14 -> 0
C15: =IFERROR(B15/SUM($B$6:$B$20),0) -> 0 | G15: =C15*D15 -> 0 | H15: =C15*E15 -> 0
C16: =IFERROR(B16/SUM($B$6:$B$20),0) -> 0 | G16: =C16*D16 -> 0 | H16: =C16*E16 -> 0
C17: =IFERROR(B17/SUM($B$6:$B$20),0) -> 0 | G17: =C17*D17 -> 0 | H17: =C17*E17 -> 0
C18: =IFERROR(B18/SUM($B$6:$B$20),0) -> 0 | G18: =C18*D18 -> 0 | H18: =C18*E18 -> 0
C19: =IFERROR(B19/SUM($B$6:$B$20),0) -> 0 | G19: =C19*D19 -> 0 | H19: =C19*E19 -> 0
C20: =IFERROR(B20/SUM($B$6:$B$20),0) -> 0 | G20: =C20*D20 -> 0 | H20: =C20*E20 -> 0
A22: Portfolio Duration | B22: =SUM(G6:G20) -> 4.7621935
A23: Portfolio Risk Score | B23: =SUM(H6:H20) -> 2.093266
A24: Portfolio Risk Level | B24: =IF(B23<=2.5,"Χαμηλός",IF(B23<=4.5,"Μέσος","Υψηλός")) -> Χαμηλός

Sheet Sources_Notes
A1: ΠΗΓΕΣ, ΤΥΠΟΙ ΚΑΙ ΟΔΗΓΙΕΣ
A3: Πώς χρησιμοποιείται
A4: 1 | B4: Συμπλήρωσε τα κίτρινα κελιά στο Inputs.
A5: 2 | B5: Δες το Dashboard για αγορά/πώληση/διακράτηση και επίπεδο κινδύνου.
A6: 3 | B6: Άλλαξε το r, το MP, το κουπόνι, το rating και το Δy για να δεις πώς αλλάζει το αποτέλεσμα.
A7: 4 | B7: Για εταιρικά/subordinated/callable ή χαμηλής ρευστότητας ομόλογα, το risk score αυξάνεται.
A8: 5 | B8: Το συμπέρασμα είναι κανόνας αξιολόγησης και όχι βέβαιη πρόβλεψη αγοράς.
A10: Βασικοί τύποι που έχουν ενσωματωθεί
A11: Intrinsic Value | B11: PV κουπονιών + PV ονομαστικής αξίας με απαιτούμενη απόδοση r.
A12: Current Yield | B12: Ετήσιο κουπόνι / MP.
A13: YTM | B13: RATE(periods, coupon per period, -price, FV) × frequency.
A14: AYTM | B14: (C + (FV-MP)/n) / ((FV+MP)/2).
A15: RCY | B15: ((FV + μελλοντική αξία επανεπενδυμένων κουπονιών) / καθαρό κόστος)^(1/n) - 1.
A16: Macaulay Duration | B16: Σύνολο: χρόνος × βάρος παρούσας αξίας cash flow.
A17: Modified Duration | B17: Macaulay Duration / (1 + YTM/frequency).
A18: Price impact | B18: %ΔP ≈ -Modified Duration × Δy.
A20: Ενδεικτικές εξωτερικές πηγές για τους οικονομικούς όρους
A21: Investor.gov - Bonds FAQ | B21: https://www.investor.gov/introduction-investing/investing-basics/investment-products/bonds-or-fixed-income-products/bonds | C21: Κουπόνια, λήξη, βασικές έννοιες ομολόγων.
A22: Investor.gov - Interest rates and fixed-rate bond prices | B22: https://www.investor.gov/introduction-investing/general-resources/news-alerts/alerts-bulletins/investor-bulletins-86 | C22: Αντίστροφη σχέση επιτοκίων/αποδόσεων και τιμών ομολόγων.
A23: CFI - Yield to Maturity | B23: https://corporatefinanceinstitute.com/resources/fixed-income/yield-to-maturity-ytm/ | C23: Έννοια YTM.
A24: Wall Street Prep - Approximate YTM | B24: https://www.wallstreetprep.com/knowledge/yield-to-maturity-ytm/ | C24: Προσεγγιστικός τύπος AYTM.
A25: CFI - Duration | B25: https://corporatefinanceinstitute.com/resources/fixed-income/duration/ | C25: Macaulay/Modified Duration και ευαισθησία τιμής.

Sheet Lists
A1: Bond Type | C1: Seniority | E1: Callable | G1: Liquidity | I1: Rating | K1: Βάση αξιολόγησης | M1: Currency | O1: Rating | P1: Score | R1: Liquidity | S1: Score | U1: Seniority | V1: Score | X1: Callable | Y1: Score | AA1: Bond Type | AB1: Score
A2: Treasury/Government | C2: Senior | E2: Ναι | G2: Υψηλή | I2: AAA | K2: Αγορά | M2: EUR | O2: AAA | P2: 1 | R2: Υψηλή | S2: 1 | U2: Senior | V2: 1 | X2: Ναι | Y2: 4 | AA2: Treasury/Government | AB2: 1
A3: Corporate | C3: Subordinated | E3: Όχι | G3: Μέση | I3: AA | K3: Πώληση | M3: USD | O3: AA | P3: 1.5 | R3: Μέση | S3: 3 | U3: Subordinated | V3: 5 | X3: Όχι | Y3: 1 | AA3: Municipal/Local Authority | AB3: 3
A4: Municipal/Local Authority | G4: Χαμηλή | I4: A | K4: Διακράτηση | M4: GBP | O4: A | P4: 2 | R4: Χαμηλή | S4: 6 | AA4: Corporate | AB4: 4
I5: BBB | M5: CHF | O5: BBB | P5: 3
I6: BB | M6: Other | O6: BB | P6: 5
I7: B | O7: B | P7: 7
I8: CCC | O8: CCC | P8: 9
I9: CC | O9: CC | P9: 10
I10: C | O10: C | P10: 10
I11: Not rated | O11: Not rated | P11: 7
